{
    "schedule": {
        "lambda_schedules": [
            {
                "qA": 1.0,
                "qB": 0.0,
                "vdwA": 1.0,
                "vdwB": 0.0
            },
            {
                "qA": 0.8,
                "qB": 0.0,
                "vdwA": 1.0,
                "vdwB": 0.08992
            },
            {
                "qA": 0.6,
                "qB": 0.0,
                "vdwA": 1.0,
                "vdwB": 0.16416
            },
            {
                "qA": 0.3999999999999999,
                "qB": 0.0,
                "vdwA": 1.0,
                "vdwB": 0.22944000000000003
            },
            {
                "qA": 0.19999999999999996,
                "qB": 0.0,
                "vdwA": 1.0,
                "vdwB": 0.29248
            },
            {
                "qA": 0.0,
                "qB": 0.0,
                "vdwA": 1.0,
                "vdwB": 0.36
            },
            {
                "qA": 0.0,
                "qB": 0.0,
                "vdwA": 0.80928,
                "vdwB": 0.4387200000000001
            },
            {
                "qA": 0.0,
                "qB": 0.0,
                "vdwA": 0.65664,
                "vdwB": 0.5353600000000001
            },
            {
                "qA": 0.0,
                "qB": 0.0,
                "vdwA": 0.5353600000000001,
                "vdwB": 0.65664
            },
            {
                "qA": 0.0,
                "qB": 0.0,
                "vdwA": 0.4387200000000001,
                "vdwB": 0.80928
            },
            {
                "qA": 0.0,
                "qB": 0.0,
                "vdwA": 0.36,
                "vdwB": 1.0
            },
            {
                "qA": 0.0,
                "qB": 0.19999999999999996,
                "vdwA": 0.29248,
                "vdwB": 1.0
            },
            {
                "qA": 0.0,
                "qB": 0.3999999999999999,
                "vdwA": 0.22944000000000003,
                "vdwB": 1.0
            },
            {
                "qA": 0.0,
                "qB": 0.6,
                "vdwA": 0.16416,
                "vdwB": 1.0
            },
            {
                "qA": 0.0,
                "qB": 0.8,
                "vdwA": 0.08992,
                "vdwB": 1.0
            },
            {
                "qA": 0.0,
                "qB": 1.0,
                "vdwA": 0.0,
                "vdwB": 1.0
            }
        ],
        "rest2": [
            1.0,
            0.8678824299399059,
            0.7463631225084788,
            0.6447016124233946,
            0.5694799785803535,
            0.5232641161420819,
            0.5032650086273591,
            0.5,
            0.5,
            0.5032650086273591,
            0.5232641161420819,
            0.5694799785803535,
            0.6447016124233946,
            0.7463631225084788,
            0.8678824299399059,
            1.0
        ]
    }
}